LICENSE.txt
MANIFEST.in
README.rst
setup.cfg
setup.py
version.txt
docs/AUTHORS.txt
docs/HISTORY.rst
docs/INSTALL.rst
docs/LICENSE.GPL
vnccollab/__init__.py
vnccollab.theme.egg-info/PKG-INFO
vnccollab.theme.egg-info/SOURCES.txt
vnccollab.theme.egg-info/dependency_links.txt
vnccollab.theme.egg-info/entry_points.txt
vnccollab.theme.egg-info/namespace_packages.txt
vnccollab.theme.egg-info/not-zip-safe
vnccollab.theme.egg-info/requires.txt
vnccollab.theme.egg-info/top_level.txt
vnccollab/theme/__init__.py
vnccollab/theme/avatar.py
vnccollab/theme/config.py
vnccollab/theme/configure.zcml
vnccollab/theme/events.zcml
vnccollab/theme/implements.zcml
vnccollab/theme/indexers.py
vnccollab/theme/overrides.zcml
vnccollab/theme/profiles.zcml
vnccollab/theme/settings.py
vnccollab/theme/setuphandlers.py
vnccollab/theme/skins.zcml
vnccollab/theme/testing.py
vnccollab/theme/userdataschema.py
vnccollab/theme/util.py
vnccollab/theme/version.txt
vnccollab/theme/vocabularies.py
vnccollab/theme/zimbrautil.py
vnccollab/theme/Extensions/install.py
vnccollab/theme/browser/__init__.py
vnccollab/theme/browser/autocomplete.py
vnccollab/theme/browser/chat.py
vnccollab/theme/browser/configure.zcml
vnccollab/theme/browser/dashboard.py
vnccollab/theme/browser/dashlet.py
vnccollab/theme/browser/file_issue.py
vnccollab/theme/browser/homepage.py
vnccollab/theme/browser/imdetails.py
vnccollab/theme/browser/interfaces.py
vnccollab/theme/browser/like.py
vnccollab/theme/browser/livesearch.py
vnccollab/theme/browser/newticket.py
vnccollab/theme/browser/newticket.view.py
vnccollab/theme/browser/notices.py
vnccollab/theme/browser/portlet_manager.py
vnccollab/theme/browser/search_contacts.py
vnccollab/theme/browser/stream.py
vnccollab/theme/browser/util.py
vnccollab/theme/browser/viewlets.py
vnccollab/theme/browser/wizardjson.py
vnccollab/theme/browser/wizarduploader.py
vnccollab/theme/browser/wsapi.py
vnccollab/theme/browser/zimbra.py
vnccollab/theme/browser/zimbrajson.py
vnccollab/theme/browser/zimbratask.py
vnccollab/theme/browser/images/README.txt
vnccollab/theme/browser/images/action-fav.png
vnccollab/theme/browser/images/doc.png
vnccollab/theme/browser/images/reload.png
vnccollab/theme/browser/images/select-icons.png
vnccollab/theme/browser/images/small_rarrow.png
vnccollab/theme/browser/images/spinner.gif
