Metadata-Version: 1.1
Name: vnccollab.theme
Version: 1.7.12
Summary: An installable theme for VNC Collaboration Plone 4 Site.
Home-page: https://github.com/vnc-biz/vnccollab.theme
Author: Vitaliy Podoba
Author-email: vitaliy.podoba@vnc.biz
License: GPL
Keywords: web zope plone theme
Platform: UNKNOWN
Classifier: Framework :: Plone
Classifier: Programming Language :: Python
